stablex/__init__.py
stablex/degree_of_freedom.py
stablex/elements/element.py
stablex/elements/spring_elements/rotational_spring_element.py
stablex/elements/spring_elements/spring_element.py
stablex/elements/unidimensional_elements/frame_element.py
stablex/elements/unidimensional_elements/truss_element.py
stablex/elements/unidimensional_elements/unidimensional_element.py
stablex/loads/load.py
stablex/node.py
stablex/section.py
stablex/solver/eigen_solver.py
stablex/solver/first_order_solver.py
stablex/solver/nonlinear_solver.py
stablex/stability_functions.py
stablex/structure.py
stablex/visualization/__init__.py
stablex/visualization/image.png
stablex/visualization/image2.png
stablex/visualization/visual_element.py
stablex/visualization/visual_element_factory.py
stablex/visualization/visual_rotational_spring_element.py
stablex/visualization/visual_unidimensional_element.py
stablex/visualization/visualizer.py
stablex-0.1.3.dist-info/LICENSE
stablex-0.1.3.dist-info/METADATA
stablex-0.1.3.dist-info/WHEEL
stablex-0.1.3.dist-info/RECORD
