Metadata-Version: 2.1
Name: stableX
Version: 0.1.3
Summary: A Python library for stability analysis of structures
Home-page: https://github.com/Hazem-Kassab/stableX
License: MIT
Author: Hazem Kassab
Requires-Python: >=3.9,<4.0
Classifier: License :: OSI Approved :: MIT License
Classifier: Programming Language :: Python :: 3
Classifier: Programming Language :: Python :: 3.9
Classifier: Programming Language :: Python :: 3.10
Classifier: Programming Language :: Python :: 3.11
Classifier: Programming Language :: Python :: 3.12
Classifier: Programming Language :: Python :: 3.13
Requires-Dist: matplotlib (>=3.9.0,<4.0.0)
Requires-Dist: numpy (>=1.25.0,<2.0.0)
